{
  "openapi": "3.0.1",
  "info": {
    "title": "apiVideojuegos",
    "version": "1.0"
  },
  "paths": {
    "/api/Categorias/GetAllCategorias": {
      "get": {
        "tags": [
          "Categorias"
        ],
        "responses": {
          "200": {
            "description": "Success",
            "content": {
              "text/plain": {
                "schema": {
                  "type": "array",
                  "items": {
                    "$ref": "#/components/schemas/CategoriasDataResponse"
                  }
                }
              },
              "application/json": {
                "schema": {
                  "type": "array",
                  "items": {
                    "$ref": "#/components/schemas/CategoriasDataResponse"
                  }
                }
              },
              "text/json": {
                "schema": {
                  "type": "array",
                  "items": {
                    "$ref": "#/components/schemas/CategoriasDataResponse"
                  }
                }
              }
            }
          }
        }
      }
    },
    "/api/Categorias/GetOneCategorias/{CategoriaId}": {
      "get": {
        "tags": [
          "Categorias"
        ],
        "parameters": [
          {
            "name": "CategoriaId",
            "in": "path",
            "required": true,
            "schema": {
              "type": "integer",
              "format": "int32"
            }
          }
        ],
        "responses": {
          "200": {
            "description": "Success",
            "content": {
              "text/plain": {
                "schema": {
                  "$ref": "#/components/schemas/CategoriasOneResponse"
                }
              },
              "application/json": {
                "schema": {
                  "$ref": "#/components/schemas/CategoriasOneResponse"
                }
              },
              "text/json": {
                "schema": {
                  "$ref": "#/components/schemas/CategoriasOneResponse"
                }
              }
            }
          }
        }
      }
    },
    "/api/Categorias/CreateCategorias": {
      "post": {
        "tags": [
          "Categorias"
        ],
        "requestBody": {
          "content": {
            "application/json": {
              "schema": {
                "$ref": "#/components/schemas/CategoriaRequest"
              }
            },
            "text/json": {
              "schema": {
                "$ref": "#/components/schemas/CategoriaRequest"
              }
            },
            "application/*+json": {
              "schema": {
                "$ref": "#/components/schemas/CategoriaRequest"
              }
            }
          }
        },
        "responses": {
          "201": {
            "description": "Created",
            "content": {
              "text/plain": {
                "schema": {
                  "type": "string"
                }
              },
              "application/json": {
                "schema": {
                  "type": "string"
                }
              },
              "text/json": {
                "schema": {
                  "type": "string"
                }
              }
            }
          }
        }
      }
    },
    "/api/Categorias/UpdateCategorias/{CategoriaId}": {
      "put": {
        "tags": [
          "Categorias"
        ],
        "parameters": [
          {
            "name": "CategoriaId",
            "in": "path",
            "required": true,
            "schema": {
              "type": "integer",
              "format": "int32"
            }
          }
        ],
        "requestBody": {
          "content": {
            "application/json": {
              "schema": {
                "$ref": "#/components/schemas/CategoriaRequest"
              }
            },
            "text/json": {
              "schema": {
                "$ref": "#/components/schemas/CategoriaRequest"
              }
            },
            "application/*+json": {
              "schema": {
                "$ref": "#/components/schemas/CategoriaRequest"
              }
            }
          }
        },
        "responses": {
          "200": {
            "description": "Success",
            "content": {
              "text/plain": {
                "schema": {
                  "type": "string"
                }
              },
              "application/json": {
                "schema": {
                  "type": "string"
                }
              },
              "text/json": {
                "schema": {
                  "type": "string"
                }
              }
            }
          }
        }
      }
    },
    "/api/Categorias/DeleteCategorias/{CategoriaId}": {
      "delete": {
        "tags": [
          "Categorias"
        ],
        "parameters": [
          {
            "name": "CategoriaId",
            "in": "path",
            "required": true,
            "schema": {
              "type": "integer",
              "format": "int32"
            }
          }
        ],
        "responses": {
          "200": {
            "description": "Success",
            "content": {
              "text/plain": {
                "schema": {
                  "type": "string"
                }
              },
              "application/json": {
                "schema": {
                  "type": "string"
                }
              },
              "text/json": {
                "schema": {
                  "type": "string"
                }
              }
            }
          }
        }
      }
    },
    "/api/Clientes/GetAllClientes": {
      "get": {
        "tags": [
          "Clientes"
        ],
        "responses": {
          "200": {
            "description": "Success",
            "content": {
              "text/plain": {
                "schema": {
                  "type": "array",
                  "items": {
                    "$ref": "#/components/schemas/ClienteDataResponse"
                  }
                }
              },
              "application/json": {
                "schema": {
                  "type": "array",
                  "items": {
                    "$ref": "#/components/schemas/ClienteDataResponse"
                  }
                }
              },
              "text/json": {
                "schema": {
                  "type": "array",
                  "items": {
                    "$ref": "#/components/schemas/ClienteDataResponse"
                  }
                }
              }
            }
          }
        }
      }
    },
    "/api/Clientes/GetOneClientes/{ClienteId}": {
      "get": {
        "tags": [
          "Clientes"
        ],
        "parameters": [
          {
            "name": "ClienteId",
            "in": "path",
            "required": true,
            "schema": {
              "type": "integer",
              "format": "int32"
            }
          }
        ],
        "responses": {
          "200": {
            "description": "Success",
            "content": {
              "text/plain": {
                "schema": {
                  "$ref": "#/components/schemas/ClienteOneResponse"
                }
              },
              "application/json": {
                "schema": {
                  "$ref": "#/components/schemas/ClienteOneResponse"
                }
              },
              "text/json": {
                "schema": {
                  "$ref": "#/components/schemas/ClienteOneResponse"
                }
              }
            }
          }
        }
      }
    },
    "/api/Clientes/CreateClientes": {
      "post": {
        "tags": [
          "Clientes"
        ],
        "requestBody": {
          "content": {
            "application/json": {
              "schema": {
                "$ref": "#/components/schemas/ClienteRequest"
              }
            },
            "text/json": {
              "schema": {
                "$ref": "#/components/schemas/ClienteRequest"
              }
            },
            "application/*+json": {
              "schema": {
                "$ref": "#/components/schemas/ClienteRequest"
              }
            }
          }
        },
        "responses": {
          "201": {
            "description": "Created",
            "content": {
              "text/plain": {
                "schema": {
                  "type": "string"
                }
              },
              "application/json": {
                "schema": {
                  "type": "string"
                }
              },
              "text/json": {
                "schema": {
                  "type": "string"
                }
              }
            }
          }
        }
      }
    },
    "/api/Clientes/UpdateClientes/{ClienteId}": {
      "put": {
        "tags": [
          "Clientes"
        ],
        "parameters": [
          {
            "name": "ClienteId",
            "in": "path",
            "required": true,
            "schema": {
              "type": "integer",
              "format": "int32"
            }
          }
        ],
        "requestBody": {
          "content": {
            "application/json": {
              "schema": {
                "$ref": "#/components/schemas/ClienteRequest"
              }
            },
            "text/json": {
              "schema": {
                "$ref": "#/components/schemas/ClienteRequest"
              }
            },
            "application/*+json": {
              "schema": {
                "$ref": "#/components/schemas/ClienteRequest"
              }
            }
          }
        },
        "responses": {
          "200": {
            "description": "Success",
            "content": {
              "text/plain": {
                "schema": {
                  "type": "string"
                }
              },
              "application/json": {
                "schema": {
                  "type": "string"
                }
              },
              "text/json": {
                "schema": {
                  "type": "string"
                }
              }
            }
          }
        }
      }
    },
    "/api/Clientes/DeleteClientes/{ClienteId}": {
      "delete": {
        "tags": [
          "Clientes"
        ],
        "parameters": [
          {
            "name": "ClienteId",
            "in": "path",
            "required": true,
            "schema": {
              "type": "integer",
              "format": "int32"
            }
          }
        ],
        "responses": {
          "200": {
            "description": "Success",
            "content": {
              "text/plain": {
                "schema": {
                  "type": "string"
                }
              },
              "application/json": {
                "schema": {
                  "type": "string"
                }
              },
              "text/json": {
                "schema": {
                  "type": "string"
                }
              }
            }
          }
        }
      }
    },
    "/api/Reserva/GetAllReservas": {
      "get": {
        "tags": [
          "Reserva"
        ],
        "responses": {
          "200": {
            "description": "Success",
            "content": {
              "text/plain": {
                "schema": {
                  "type": "array",
                  "items": {
                    "$ref": "#/components/schemas/ReservaDataResponse"
                  }
                }
              },
              "application/json": {
                "schema": {
                  "type": "array",
                  "items": {
                    "$ref": "#/components/schemas/ReservaDataResponse"
                  }
                }
              },
              "text/json": {
                "schema": {
                  "type": "array",
                  "items": {
                    "$ref": "#/components/schemas/ReservaDataResponse"
                  }
                }
              }
            }
          }
        }
      }
    },
    "/api/Reserva/GetOneReservas/{ReservaId}": {
      "get": {
        "tags": [
          "Reserva"
        ],
        "parameters": [
          {
            "name": "ReservaId",
            "in": "path",
            "required": true,
            "schema": {
              "type": "integer",
              "format": "int32"
            }
          }
        ],
        "responses": {
          "200": {
            "description": "Success",
            "content": {
              "text/plain": {
                "schema": {
                  "$ref": "#/components/schemas/ReservaOneResponse"
                }
              },
              "application/json": {
                "schema": {
                  "$ref": "#/components/schemas/ReservaOneResponse"
                }
              },
              "text/json": {
                "schema": {
                  "$ref": "#/components/schemas/ReservaOneResponse"
                }
              }
            }
          }
        }
      }
    },
    "/api/Reserva/CreateReservas": {
      "post": {
        "tags": [
          "Reserva"
        ],
        "requestBody": {
          "content": {
            "application/json": {
              "schema": {
                "$ref": "#/components/schemas/ReservaRequest"
              }
            },
            "text/json": {
              "schema": {
                "$ref": "#/components/schemas/ReservaRequest"
              }
            },
            "application/*+json": {
              "schema": {
                "$ref": "#/components/schemas/ReservaRequest"
              }
            }
          }
        },
        "responses": {
          "201": {
            "description": "Created",
            "content": {
              "text/plain": {
                "schema": {
                  "type": "string"
                }
              },
              "application/json": {
                "schema": {
                  "type": "string"
                }
              },
              "text/json": {
                "schema": {
                  "type": "string"
                }
              }
            }
          }
        }
      }
    },
    "/api/Reserva/UpdateReservas/{ReservaId}": {
      "put": {
        "tags": [
          "Reserva"
        ],
        "parameters": [
          {
            "name": "ReservaId",
            "in": "path",
            "required": true,
            "schema": {
              "type": "integer",
              "format": "int32"
            }
          }
        ],
        "requestBody": {
          "content": {
            "application/json": {
              "schema": {
                "$ref": "#/components/schemas/ReservaRequest"
              }
            },
            "text/json": {
              "schema": {
                "$ref": "#/components/schemas/ReservaRequest"
              }
            },
            "application/*+json": {
              "schema": {
                "$ref": "#/components/schemas/ReservaRequest"
              }
            }
          }
        },
        "responses": {
          "200": {
            "description": "Success",
            "content": {
              "text/plain": {
                "schema": {
                  "type": "string"
                }
              },
              "application/json": {
                "schema": {
                  "type": "string"
                }
              },
              "text/json": {
                "schema": {
                  "type": "string"
                }
              }
            }
          }
        }
      }
    },
    "/api/Reserva/DeleteReservas/{ReservaId}": {
      "delete": {
        "tags": [
          "Reserva"
        ],
        "parameters": [
          {
            "name": "ReservaId",
            "in": "path",
            "required": true,
            "schema": {
              "type": "integer",
              "format": "int32"
            }
          }
        ],
        "responses": {
          "200": {
            "description": "Success",
            "content": {
              "text/plain": {
                "schema": {
                  "type": "string"
                }
              },
              "application/json": {
                "schema": {
                  "type": "string"
                }
              },
              "text/json": {
                "schema": {
                  "type": "string"
                }
              }
            }
          }
        }
      }
    },
    "/api/ReservaVideojuego/GetAllReservaVideojuego": {
      "get": {
        "tags": [
          "ReservaVideojuego"
        ],
        "responses": {
          "200": {
            "description": "Success",
            "content": {
              "text/plain": {
                "schema": {
                  "type": "array",
                  "items": {
                    "$ref": "#/components/schemas/ReservaVideojuegoDataReponse"
                  }
                }
              },
              "application/json": {
                "schema": {
                  "type": "array",
                  "items": {
                    "$ref": "#/components/schemas/ReservaVideojuegoDataReponse"
                  }
                }
              },
              "text/json": {
                "schema": {
                  "type": "array",
                  "items": {
                    "$ref": "#/components/schemas/ReservaVideojuegoDataReponse"
                  }
                }
              }
            }
          }
        }
      }
    },
    "/api/ReservaVideojuego/GetOneReservaVideojuego/{ReservaVideojuegoId}": {
      "get": {
        "tags": [
          "ReservaVideojuego"
        ],
        "parameters": [
          {
            "name": "ReservaVideojuegoId",
            "in": "path",
            "required": true,
            "schema": {
              "type": "integer",
              "format": "int32"
            }
          }
        ],
        "responses": {
          "200": {
            "description": "Success",
            "content": {
              "text/plain": {
                "schema": {
                  "$ref": "#/components/schemas/ReservaVideojuegoOneResponse"
                }
              },
              "application/json": {
                "schema": {
                  "$ref": "#/components/schemas/ReservaVideojuegoOneResponse"
                }
              },
              "text/json": {
                "schema": {
                  "$ref": "#/components/schemas/ReservaVideojuegoOneResponse"
                }
              }
            }
          }
        }
      }
    },
    "/api/ReservaVideojuego/CreateReservas": {
      "post": {
        "tags": [
          "ReservaVideojuego"
        ],
        "requestBody": {
          "content": {
            "application/json": {
              "schema": {
                "$ref": "#/components/schemas/ReservaVideojuegoRequest"
              }
            },
            "text/json": {
              "schema": {
                "$ref": "#/components/schemas/ReservaVideojuegoRequest"
              }
            },
            "application/*+json": {
              "schema": {
                "$ref": "#/components/schemas/ReservaVideojuegoRequest"
              }
            }
          }
        },
        "responses": {
          "201": {
            "description": "Created",
            "content": {
              "text/plain": {
                "schema": {
                  "$ref": "#/components/schemas/Reserva"
                }
              },
              "application/json": {
                "schema": {
                  "$ref": "#/components/schemas/Reserva"
                }
              },
              "text/json": {
                "schema": {
                  "$ref": "#/components/schemas/Reserva"
                }
              }
            }
          }
        }
      }
    },
    "/api/ReservaVideojuego/UpdateReservas/{ReservaVideojuegoId}": {
      "put": {
        "tags": [
          "ReservaVideojuego"
        ],
        "parameters": [
          {
            "name": "ReservaVideojuegoId",
            "in": "path",
            "required": true,
            "schema": {
              "type": "integer",
              "format": "int32"
            }
          }
        ],
        "requestBody": {
          "content": {
            "application/json": {
              "schema": {
                "$ref": "#/components/schemas/ReservaVideojuegoRequest"
              }
            },
            "text/json": {
              "schema": {
                "$ref": "#/components/schemas/ReservaVideojuegoRequest"
              }
            },
            "application/*+json": {
              "schema": {
                "$ref": "#/components/schemas/ReservaVideojuegoRequest"
              }
            }
          }
        },
        "responses": {
          "200": {
            "description": "Success",
            "content": {
              "text/plain": {
                "schema": {
                  "type": "string"
                }
              },
              "application/json": {
                "schema": {
                  "type": "string"
                }
              },
              "text/json": {
                "schema": {
                  "type": "string"
                }
              }
            }
          }
        }
      }
    },
    "/api/ReservaVideojuego/DeleteReservaVideojuego/{ReservaVideojuegoId}": {
      "delete": {
        "tags": [
          "ReservaVideojuego"
        ],
        "parameters": [
          {
            "name": "ReservaVideojuegoId",
            "in": "path",
            "required": true,
            "schema": {
              "type": "integer",
              "format": "int32"
            }
          }
        ],
        "responses": {
          "200": {
            "description": "Success",
            "content": {
              "text/plain": {
                "schema": {
                  "type": "string"
                }
              },
              "application/json": {
                "schema": {
                  "type": "string"
                }
              },
              "text/json": {
                "schema": {
                  "type": "string"
                }
              }
            }
          }
        }
      }
    },
    "/api/Usuarios/GetAllUsuarios": {
      "get": {
        "tags": [
          "Usuarios"
        ],
        "responses": {
          "200": {
            "description": "Success",
            "content": {
              "text/plain": {
                "schema": {
                  "type": "array",
                  "items": {
                    "$ref": "#/components/schemas/UsuarioDataResponse"
                  }
                }
              },
              "application/json": {
                "schema": {
                  "type": "array",
                  "items": {
                    "$ref": "#/components/schemas/UsuarioDataResponse"
                  }
                }
              },
              "text/json": {
                "schema": {
                  "type": "array",
                  "items": {
                    "$ref": "#/components/schemas/UsuarioDataResponse"
                  }
                }
              }
            }
          }
        }
      }
    },
    "/api/Usuarios/GetOneUsuarios/{UsuarioId}": {
      "get": {
        "tags": [
          "Usuarios"
        ],
        "parameters": [
          {
            "name": "UsuarioId",
            "in": "path",
            "required": true,
            "schema": {
              "type": "integer",
              "format": "int32"
            }
          }
        ],
        "responses": {
          "200": {
            "description": "Success",
            "content": {
              "text/plain": {
                "schema": {
                  "$ref": "#/components/schemas/UsuarioOneResponse"
                }
              },
              "application/json": {
                "schema": {
                  "$ref": "#/components/schemas/UsuarioOneResponse"
                }
              },
              "text/json": {
                "schema": {
                  "$ref": "#/components/schemas/UsuarioOneResponse"
                }
              }
            }
          }
        }
      }
    },
    "/api/Usuarios/CreateUsuarios": {
      "post": {
        "tags": [
          "Usuarios"
        ],
        "requestBody": {
          "content": {
            "application/json": {
              "schema": {
                "$ref": "#/components/schemas/UsuariosRequest"
              }
            },
            "text/json": {
              "schema": {
                "$ref": "#/components/schemas/UsuariosRequest"
              }
            },
            "application/*+json": {
              "schema": {
                "$ref": "#/components/schemas/UsuariosRequest"
              }
            }
          }
        },
        "responses": {
          "201": {
            "description": "Created",
            "content": {
              "text/plain": {
                "schema": {
                  "type": "string"
                }
              },
              "application/json": {
                "schema": {
                  "type": "string"
                }
              },
              "text/json": {
                "schema": {
                  "type": "string"
                }
              }
            }
          }
        }
      }
    },
    "/api/Usuarios/UpdateUsuarios/{UsuarioId}": {
      "put": {
        "tags": [
          "Usuarios"
        ],
        "parameters": [
          {
            "name": "UsuarioId",
            "in": "path",
            "required": true,
            "schema": {
              "type": "integer",
              "format": "int32"
            }
          }
        ],
        "requestBody": {
          "content": {
            "application/json": {
              "schema": {
                "$ref": "#/components/schemas/UsuariosRequest"
              }
            },
            "text/json": {
              "schema": {
                "$ref": "#/components/schemas/UsuariosRequest"
              }
            },
            "application/*+json": {
              "schema": {
                "$ref": "#/components/schemas/UsuariosRequest"
              }
            }
          }
        },
        "responses": {
          "200": {
            "description": "Success",
            "content": {
              "text/plain": {
                "schema": {
                  "type": "string"
                }
              },
              "application/json": {
                "schema": {
                  "type": "string"
                }
              },
              "text/json": {
                "schema": {
                  "type": "string"
                }
              }
            }
          }
        }
      }
    },
    "/api/Usuarios/DeleteUsuarios/{UsuarioId}": {
      "delete": {
        "tags": [
          "Usuarios"
        ],
        "parameters": [
          {
            "name": "UsuarioId",
            "in": "path",
            "required": true,
            "schema": {
              "type": "integer",
              "format": "int32"
            }
          }
        ],
        "responses": {
          "200": {
            "description": "Success",
            "content": {
              "text/plain": {
                "schema": {
                  "type": "string"
                }
              },
              "application/json": {
                "schema": {
                  "type": "string"
                }
              },
              "text/json": {
                "schema": {
                  "type": "string"
                }
              }
            }
          }
        }
      }
    },
    "/api/Usuarios/Login": {
      "post": {
        "tags": [
          "Usuarios"
        ],
        "requestBody": {
          "content": {
            "application/json": {
              "schema": {
                "$ref": "#/components/schemas/LoginRequest"
              }
            },
            "text/json": {
              "schema": {
                "$ref": "#/components/schemas/LoginRequest"
              }
            },
            "application/*+json": {
              "schema": {
                "$ref": "#/components/schemas/LoginRequest"
              }
            }
          }
        },
        "responses": {
          "200": {
            "description": "Success"
          }
        }
      }
    },
    "/api/Videojuegos/GetAllVideojuegos": {
      "get": {
        "tags": [
          "Videojuegos"
        ],
        "responses": {
          "200": {
            "description": "Success",
            "content": {
              "text/plain": {
                "schema": {
                  "type": "array",
                  "items": {
                    "$ref": "#/components/schemas/VideojuegosDataResponse"
                  }
                }
              },
              "application/json": {
                "schema": {
                  "type": "array",
                  "items": {
                    "$ref": "#/components/schemas/VideojuegosDataResponse"
                  }
                }
              },
              "text/json": {
                "schema": {
                  "type": "array",
                  "items": {
                    "$ref": "#/components/schemas/VideojuegosDataResponse"
                  }
                }
              }
            }
          }
        }
      }
    },
    "/api/Videojuegos/GetOneVideojuegos/{VideojuegoId}": {
      "get": {
        "tags": [
          "Videojuegos"
        ],
        "parameters": [
          {
            "name": "VideojuegoId",
            "in": "path",
            "required": true,
            "schema": {
              "type": "integer",
              "format": "int32"
            }
          }
        ],
        "responses": {
          "200": {
            "description": "Success",
            "content": {
              "text/plain": {
                "schema": {
                  "$ref": "#/components/schemas/VideojuegosOneResponse"
                }
              },
              "application/json": {
                "schema": {
                  "$ref": "#/components/schemas/VideojuegosOneResponse"
                }
              },
              "text/json": {
                "schema": {
                  "$ref": "#/components/schemas/VideojuegosOneResponse"
                }
              }
            }
          }
        }
      }
    },
    "/api/Videojuegos/CreateVideojuegos": {
      "post": {
        "tags": [
          "Videojuegos"
        ],
        "requestBody": {
          "content": {
            "application/json": {
              "schema": {
                "$ref": "#/components/schemas/VideojuegosRequest"
              }
            },
            "text/json": {
              "schema": {
                "$ref": "#/components/schemas/VideojuegosRequest"
              }
            },
            "application/*+json": {
              "schema": {
                "$ref": "#/components/schemas/VideojuegosRequest"
              }
            }
          }
        },
        "responses": {
          "201": {
            "description": "Created",
            "content": {
              "text/plain": {
                "schema": {
                  "type": "string"
                }
              },
              "application/json": {
                "schema": {
                  "type": "string"
                }
              },
              "text/json": {
                "schema": {
                  "type": "string"
                }
              }
            }
          }
        }
      }
    },
    "/api/Videojuegos/UpdateVideojuegos/{VideojuegoId}": {
      "put": {
        "tags": [
          "Videojuegos"
        ],
        "parameters": [
          {
            "name": "VideojuegoId",
            "in": "path",
            "required": true,
            "schema": {
              "type": "integer",
              "format": "int32"
            }
          }
        ],
        "requestBody": {
          "content": {
            "application/json": {
              "schema": {
                "$ref": "#/components/schemas/VideojuegosRequest"
              }
            },
            "text/json": {
              "schema": {
                "$ref": "#/components/schemas/VideojuegosRequest"
              }
            },
            "application/*+json": {
              "schema": {
                "$ref": "#/components/schemas/VideojuegosRequest"
              }
            }
          }
        },
        "responses": {
          "200": {
            "description": "Success",
            "content": {
              "text/plain": {
                "schema": {
                  "type": "string"
                }
              },
              "application/json": {
                "schema": {
                  "type": "string"
                }
              },
              "text/json": {
                "schema": {
                  "type": "string"
                }
              }
            }
          }
        }
      }
    },
    "/api/Videojuegos/DeleteVideojuegos/{VideojuegoId}": {
      "delete": {
        "tags": [
          "Videojuegos"
        ],
        "parameters": [
          {
            "name": "VideojuegoId",
            "in": "path",
            "required": true,
            "schema": {
              "type": "integer",
              "format": "int32"
            }
          }
        ],
        "responses": {
          "200": {
            "description": "Success",
            "content": {
              "text/plain": {
                "schema": {
                  "type": "string"
                }
              },
              "application/json": {
                "schema": {
                  "type": "string"
                }
              },
              "text/json": {
                "schema": {
                  "type": "string"
                }
              }
            }
          }
        }
      }
    },
    "/WeatherForecast": {
      "get": {
        "tags": [
          "WeatherForecast"
        ],
        "operationId": "GetWeatherForecast",
        "responses": {
          "200": {
            "description": "Success",
            "content": {
              "text/plain": {
                "schema": {
                  "type": "array",
                  "items": {
                    "$ref": "#/components/schemas/WeatherForecast"
                  }
                }
              },
              "application/json": {
                "schema": {
                  "type": "array",
                  "items": {
                    "$ref": "#/components/schemas/WeatherForecast"
                  }
                }
              },
              "text/json": {
                "schema": {
                  "type": "array",
                  "items": {
                    "$ref": "#/components/schemas/WeatherForecast"
                  }
                }
              }
            }
          }
        }
      }
    }
  },
  "components": {
    "schemas": {
      "CategoriaRequest": {
        "type": "object",
        "properties": {
          "nombreCategoria": {
            "type": "string",
            "nullable": true
          },
          "descripcion": {
            "type": "string",
            "nullable": true
          }
        },
        "additionalProperties": false
      },
      "CategoriasDataResponse": {
        "type": "object",
        "properties": {
          "categoriaId": {
            "type": "integer",
            "format": "int32"
          },
          "nombreCategoria": {
            "type": "string",
            "nullable": true
          },
          "descripcion": {
            "type": "string",
            "nullable": true
          }
        },
        "additionalProperties": false
      },
      "CategoriasOneResponse": {
        "type": "object",
        "properties": {
          "categoriaId": {
            "type": "integer",
            "format": "int32"
          },
          "nombreCategoria": {
            "type": "string",
            "nullable": true
          },
          "descripcion": {
            "type": "string",
            "nullable": true
          }
        },
        "additionalProperties": false
      },
      "ClienteDataResponse": {
        "type": "object",
        "properties": {
          "clienteId": {
            "type": "integer",
            "format": "int32"
          },
          "nombre": {
            "type": "string",
            "nullable": true
          },
          "documento": {
            "type": "string",
            "nullable": true
          },
          "telefono": {
            "type": "string",
            "nullable": true
          },
          "email": {
            "type": "string",
            "nullable": true
          },
          "fechaRegistro": {
            "type": "string",
            "format": "date-time"
          }
        },
        "additionalProperties": false
      },
      "ClienteOneResponse": {
        "type": "object",
        "properties": {
          "clienteId": {
            "type": "integer",
            "format": "int32"
          },
          "nombre": {
            "type": "string",
            "nullable": true
          },
          "documento": {
            "type": "string",
            "nullable": true
          },
          "telefono": {
            "type": "string",
            "nullable": true
          },
          "email": {
            "type": "string",
            "nullable": true
          },
          "fechaRegistro": {
            "type": "string",
            "format": "date-time"
          }
        },
        "additionalProperties": false
      },
      "ClienteRequest": {
        "type": "object",
        "properties": {
          "nombre": {
            "type": "string",
            "nullable": true
          },
          "documento": {
            "type": "string",
            "nullable": true
          },
          "telefono": {
            "type": "string",
            "nullable": true
          },
          "email": {
            "type": "string",
            "nullable": true
          }
        },
        "additionalProperties": false
      },
      "LoginRequest": {
        "type": "object",
        "properties": {
          "nombre": {
            "type": "string",
            "nullable": true
          },
          "clave": {
            "type": "string",
            "nullable": true
          }
        },
        "additionalProperties": false
      },
      "Reserva": {
        "type": "object",
        "properties": {
          "reservaId": {
            "type": "integer",
            "format": "int32"
          }
        },
        "additionalProperties": false
      },
      "ReservaDataResponse": {
        "type": "object",
        "properties": {
          "reservaId": {
            "type": "integer",
            "format": "int32"
          },
          "clienteId": {
            "type": "integer",
            "format": "int32"
          },
          "nombreCliente": {
            "type": "string",
            "nullable": true
          },
          "usuarioId": {
            "type": "integer",
            "format": "int32"
          },
          "nombreUsuario": {
            "type": "string",
            "nullable": true
          },
          "fechaReserva": {
            "type": "string",
            "format": "date-time"
          },
          "fechaLimite": {
            "type": "string",
            "format": "date-time"
          },
          "fechaReal": {
            "type": "string",
            "format": "date-time"
          },
          "estado": {
            "type": "string",
            "nullable": true
          },
          "total": {
            "type": "number",
            "format": "double"
          }
        },
        "additionalProperties": false
      },
      "ReservaOneResponse": {
        "type": "object",
        "properties": {
          "reservaId": {
            "type": "integer",
            "format": "int32"
          },
          "clienteId": {
            "type": "integer",
            "format": "int32"
          },
          "nombreCliente": {
            "type": "string",
            "nullable": true
          },
          "usuarioId": {
            "type": "integer",
            "format": "int32"
          },
          "nombreUsuario": {
            "type": "string",
            "nullable": true
          },
          "fechaReserva": {
            "type": "string",
            "format": "date-time"
          },
          "fechaLimite": {
            "type": "string",
            "format": "date-time"
          },
          "fechaReal": {
            "type": "string",
            "format": "date-time"
          },
          "estado": {
            "type": "string",
            "nullable": true
          },
          "total": {
            "type": "number",
            "format": "double"
          }
        },
        "additionalProperties": false
      },
      "ReservaRequest": {
        "type": "object",
        "properties": {
          "clienteId": {
            "type": "integer",
            "format": "int32"
          },
          "usuarioId": {
            "type": "integer",
            "format": "int32"
          },
          "fechaLimite": {
            "type": "string",
            "format": "date-time"
          },
          "fechaReal": {
            "type": "string",
            "format": "date-time"
          },
          "estado": {
            "type": "string",
            "nullable": true
          },
          "total": {
            "type": "number",
            "format": "double"
          }
        },
        "additionalProperties": false
      },
      "ReservaVideojuegoDataReponse": {
        "type": "object",
        "properties": {
          "reservaVideojuegoId": {
            "type": "integer",
            "format": "int32"
          },
          "reservaId": {
            "type": "integer",
            "format": "int32"
          },
          "videojuegoId": {
            "type": "integer",
            "format": "int32"
          },
          "titulo": {
            "type": "string",
            "nullable": true
          },
          "precio": {
            "type": "number",
            "format": "double"
          },
          "cantidad": {
            "type": "integer",
            "format": "int32"
          },
          "total": {
            "type": "number",
            "format": "double"
          }
        },
        "additionalProperties": false
      },
      "ReservaVideojuegoOneResponse": {
        "type": "object",
        "properties": {
          "reservaVideojuegoId": {
            "type": "integer",
            "format": "int32"
          },
          "reservaId": {
            "type": "integer",
            "format": "int32"
          },
          "videojuegoId": {
            "type": "integer",
            "format": "int32"
          },
          "titulo": {
            "type": "string",
            "nullable": true
          },
          "precio": {
            "type": "number",
            "format": "double"
          },
          "cantidad": {
            "type": "integer",
            "format": "int32"
          },
          "total": {
            "type": "number",
            "format": "double"
          }
        },
        "additionalProperties": false
      },
      "ReservaVideojuegoRequest": {
        "type": "object",
        "properties": {
          "reservaId": {
            "type": "integer",
            "format": "int32"
          },
          "videojuegoId": {
            "type": "integer",
            "format": "int32"
          },
          "cantidad": {
            "type": "integer",
            "format": "int32"
          },
          "total": {
            "type": "number",
            "format": "double"
          }
        },
        "additionalProperties": false
      },
      "UsuarioDataResponse": {
        "type": "object",
        "properties": {
          "usuarioId": {
            "type": "integer",
            "format": "int32"
          },
          "nombre": {
            "type": "string",
            "nullable": true
          },
          "usuario": {
            "type": "string",
            "nullable": true
          },
          "clave": {
            "type": "string",
            "nullable": true
          },
          "rol": {
            "type": "string",
            "nullable": true
          }
        },
        "additionalProperties": false
      },
      "UsuarioOneResponse": {
        "type": "object",
        "properties": {
          "usuarioId": {
            "type": "integer",
            "format": "int32"
          },
          "nombre": {
            "type": "string",
            "nullable": true
          },
          "usuario": {
            "type": "string",
            "nullable": true
          },
          "clave": {
            "type": "string",
            "nullable": true
          },
          "rol": {
            "type": "string",
            "nullable": true
          }
        },
        "additionalProperties": false
      },
      "UsuariosRequest": {
        "type": "object",
        "properties": {
          "nombre": {
            "type": "string",
            "nullable": true
          },
          "usuario": {
            "type": "string",
            "nullable": true
          },
          "clave": {
            "type": "string",
            "nullable": true
          },
          "rol": {
            "type": "string",
            "nullable": true
          }
        },
        "additionalProperties": false
      },
      "VideojuegosDataResponse": {
        "type": "object",
        "properties": {
          "videojuegoId": {
            "type": "integer",
            "format": "int32"
          },
          "titulo": {
            "type": "string",
            "nullable": true
          },
          "genero": {
            "type": "string",
            "nullable": true
          },
          "plataforma": {
            "type": "string",
            "nullable": true
          },
          "stock": {
            "type": "integer",
            "format": "int32"
          },
          "precio": {
            "type": "number",
            "format": "double"
          },
          "fechaLanzamiento": {
            "type": "string",
            "format": "date-time",
            "nullable": true
          },
          "categoriaId": {
            "type": "integer",
            "format": "int32"
          },
          "nombreCategoria": {
            "type": "string",
            "nullable": true
          }
        },
        "additionalProperties": false
      },
      "VideojuegosOneResponse": {
        "type": "object",
        "properties": {
          "videojuegoId": {
            "type": "integer",
            "format": "int32"
          },
          "titulo": {
            "type": "string",
            "nullable": true
          },
          "genero": {
            "type": "string",
            "nullable": true
          },
          "plataforma": {
            "type": "string",
            "nullable": true
          },
          "stock": {
            "type": "integer",
            "format": "int32"
          },
          "precio": {
            "type": "number",
            "format": "double"
          },
          "fechaLanzamiento": {
            "type": "string",
            "format": "date-time",
            "nullable": true
          },
          "categoriaId": {
            "type": "integer",
            "format": "int32"
          },
          "nombreCategoria": {
            "type": "string",
            "nullable": true
          }
        },
        "additionalProperties": false
      },
      "VideojuegosRequest": {
        "type": "object",
        "properties": {
          "titulo": {
            "type": "string",
            "nullable": true
          },
          "genero": {
            "type": "string",
            "nullable": true
          },
          "plataforma": {
            "type": "string",
            "nullable": true
          },
          "stock": {
            "type": "integer",
            "format": "int32"
          },
          "precio": {
            "type": "number",
            "format": "double"
          },
          "fechaLanzamiento": {
            "type": "string",
            "format": "date-time",
            "nullable": true
          },
          "categoriaId": {
            "type": "integer",
            "format": "int32"
          }
        },
        "additionalProperties": false
      },
      "WeatherForecast": {
        "type": "object",
        "properties": {
          "date": {
            "type": "string",
            "format": "date-time"
          },
          "temperatureC": {
            "type": "integer",
            "format": "int32"
          },
          "temperatureF": {
            "type": "integer",
            "format": "int32",
            "readOnly": true
          },
          "summary": {
            "type": "string",
            "nullable": true
          }
        },
        "additionalProperties": false
      }
    }
  }
}